fairpred/__init__.py
fairpred/fair_predictor.py
fairpred/fairpred_new.py
fairpred/load_data.py
fairpred/utils.py
fairpred-0.1.data/scripts/fairpred_new.py
fairpred-0.1.data/scripts/load_data.py
fairpred-0.1.dist-info/LICENSE
fairpred-0.1.dist-info/METADATA
fairpred-0.1.dist-info/WHEEL
fairpred-0.1.dist-info/top_level.txt
fairpred-0.1.dist-info/RECORD
