Metadata-Version: 2.1
Name: fairpred
Version: 0.1
Summary: A Column predictor with fairness
Home-page: https://github.com/schelterlabs/deml-project-10
Author: Mark J Estudillo
Author-email: markestudillo@gmail.com
License: UNKNOWN
Platform: UNKNOWN
Classifier: Programming Language :: Python :: 3
Classifier: License :: OSI Approved :: MIT License
Classifier: Operating System :: OS Independent
